{
  "schema_version": 1,
  "commit": "75990d19",
  "branch": "main",
  "os": "linux-x86_64",
  "timestamp": "2026-05-25T09:55:01Z",
  "benchmarks": [
    {
      "name": "01_fibonacci",
      "tier": "z42-e2e",
      "metric": "time",
      "value": 98.757,
      "unit": "ms",
      "ci_lower": 96.164,
      "ci_upper": 101.259,
      "samples": 10
    },
    {
      "name": "02_math_loop",
      "tier": "z42-e2e",
      "metric": "time",
      "value": 36.064,
      "unit": "ms",
      "ci_lower": 34.977,
      "ci_upper": 36.898,
      "samples": 10
    },
    {
      "name": "03_startup",
      "tier": "z42-e2e",
      "metric": "time",
      "value": 19.493,
      "unit": "ms",
      "ci_lower": 18.838,
      "ci_upper": 21.361,
      "samples": 10
    }
  ]
}
