{
  "schema_version": 1,
  "commit": "187a1e64",
  "branch": "main",
  "os": "linux-x86_64",
  "timestamp": "2026-06-24T02:45:29Z",
  "benchmarks": [
    {
      "name": "01_fibonacci",
      "tier": "z42-e2e",
      "metric": "time",
      "value": 1133.3659081,
      "unit": "ms",
      "ci_lower": 1123.041261,
      "ci_upper": 1158.454099,
      "samples": 10
    },
    {
      "name": "02_math_loop",
      "tier": "z42-e2e",
      "metric": "time",
      "value": 1092.7049553000002,
      "unit": "ms",
      "ci_lower": 1087.4522740000002,
      "ci_upper": 1111.494838,
      "samples": 10
    },
    {
      "name": "03_startup",
      "tier": "z42-e2e",
      "metric": "time",
      "value": 1089.1214008000002,
      "unit": "ms",
      "ci_lower": 1080.672851,
      "ci_upper": 1100.4692499999999,
      "samples": 10
    },
    {
      "name": "04_c2_p1_arith_loop",
      "tier": "z42-e2e",
      "metric": "time",
      "value": 743.3188158,
      "unit": "ms",
      "ci_lower": 740.759268,
      "ci_upper": 746.542131,
      "samples": 10
    },
    {
      "name": "05_polymorphic_dispatch",
      "tier": "z42-e2e",
      "metric": "time",
      "value": 2339.5558588999997,
      "unit": "ms",
      "ci_lower": 2324.80961,
      "ci_upper": 2355.3856149999997,
      "samples": 10
    }
  ]
}
