{
  "schema_version": 1,
  "commit": "f3a0021",
  "branch": "main",
  "os": "linux-x86_64",
  "timestamp": "2026-05-07T12:25:46Z",
  "benchmarks": [
    {
      "name": "01_fibonacci",
      "tier": "z42-e2e",
      "metric": "time",
      "value": 88.121,
      "unit": "ms",
      "ci_lower": 86.425,
      "ci_upper": 91.08,
      "samples": 10
    },
    {
      "name": "02_math_loop",
      "tier": "z42-e2e",
      "metric": "time",
      "value": 19.885,
      "unit": "ms",
      "ci_lower": 19.422,
      "ci_upper": 20.198,
      "samples": 10
    },
    {
      "name": "03_startup",
      "tier": "z42-e2e",
      "metric": "time",
      "value": 3.6,
      "unit": "ms",
      "ci_lower": 3.535,
      "ci_upper": 3.905,
      "samples": 10
    }
  ]
}
