{
  "schema_version": 1,
  "commit": "0787594f",
  "branch": "main",
  "os": "linux-x86_64",
  "timestamp": "2026-05-22T01:34:15Z",
  "benchmarks": [
    {
      "name": "01_fibonacci",
      "tier": "z42-e2e",
      "metric": "time",
      "value": 100.89,
      "unit": "ms",
      "ci_lower": 98.976,
      "ci_upper": 102.634,
      "samples": 10
    },
    {
      "name": "02_math_loop",
      "tier": "z42-e2e",
      "metric": "time",
      "value": 30.091,
      "unit": "ms",
      "ci_lower": 29.806,
      "ci_upper": 30.45,
      "samples": 10
    },
    {
      "name": "03_startup",
      "tier": "z42-e2e",
      "metric": "time",
      "value": 13.191,
      "unit": "ms",
      "ci_lower": 12.829,
      "ci_upper": 13.634,
      "samples": 10
    }
  ]
}
