{
  "schema_version": 1,
  "commit": "d69e6716",
  "branch": "main",
  "os": "linux-x86_64",
  "timestamp": "2026-06-15T20:57:14Z",
  "benchmarks": [
    {
      "name": "01_fibonacci",
      "tier": "z42-e2e",
      "metric": "time",
      "value": 133.5547416,
      "unit": "ms",
      "ci_lower": 131.846033,
      "ci_upper": 137.366342,
      "samples": 10
    },
    {
      "name": "02_math_loop",
      "tier": "z42-e2e",
      "metric": "time",
      "value": 60.97655410000001,
      "unit": "ms",
      "ci_lower": 59.97947500000001,
      "ci_upper": 61.799564000000004,
      "samples": 10
    },
    {
      "name": "03_startup",
      "tier": "z42-e2e",
      "metric": "time",
      "value": 45.2801906,
      "unit": "ms",
      "ci_lower": 44.509133,
      "ci_upper": 46.414256,
      "samples": 10
    },
    {
      "name": "04_c2_p1_arith_loop",
      "tier": "z42-e2e",
      "metric": "time",
      "value": 1396.9475372,
      "unit": "ms",
      "ci_lower": 1350.943217,
      "ci_upper": 1723.9094010000001,
      "samples": 10
    },
    {
      "name": "05_polymorphic_dispatch",
      "tier": "z42-e2e",
      "metric": "time",
      "value": 4206.687913000001,
      "unit": "ms",
      "ci_lower": 4092.330428,
      "ci_upper": 4283.1697030000005,
      "samples": 10
    }
  ]
}
