{
  "schema_version": 1,
  "commit": "2edee121",
  "branch": "main",
  "os": "linux-x86_64",
  "timestamp": "2026-05-31T08:00:14Z",
  "benchmarks": [
    {
      "name": "01_fibonacci",
      "tier": "z42-e2e",
      "metric": "time",
      "value": 125.396,
      "unit": "ms",
      "ci_lower": 122.299,
      "ci_upper": 128.814,
      "samples": 10
    },
    {
      "name": "02_math_loop",
      "tier": "z42-e2e",
      "metric": "time",
      "value": 60.382,
      "unit": "ms",
      "ci_lower": 58.999,
      "ci_upper": 62.742,
      "samples": 10
    },
    {
      "name": "03_startup",
      "tier": "z42-e2e",
      "metric": "time",
      "value": 43.453,
      "unit": "ms",
      "ci_lower": 42.465,
      "ci_upper": 44.093,
      "samples": 10
    },
    {
      "name": "04_c2_p1_arith_loop",
      "tier": "z42-e2e",
      "metric": "time",
      "value": 1362.817,
      "unit": "ms",
      "ci_lower": 1344.282,
      "ci_upper": 1383.29,
      "samples": 10
    },
    {
      "name": "05_polymorphic_dispatch",
      "tier": "z42-e2e",
      "metric": "time",
      "value": 4230.755,
      "unit": "ms",
      "ci_lower": 4138.192,
      "ci_upper": 4611.902,
      "samples": 10
    }
  ]
}
